esse/__init__.py
esse/_version.py
esse/settings.py
esse/utils.py
esse/data/example/element.json
esse/data/example/job.json
esse/data/example/material.json
esse/data/example/method.json
esse/data/example/model.json
esse/data/example/project.json
esse/data/example/workflow.json
esse/data/example/3pse/file/applications/espresso/7.2/pw.x.json
esse/data/example/core/reference.json
esse/data/example/core/abstract/2d_data.json
esse/data/example/core/abstract/2d_plot.json
esse/data/example/core/abstract/3d_grid.json
esse/data/example/core/abstract/3d_tensor.json
esse/data/example/core/abstract/3d_vector_basis.json
esse/data/example/core/abstract/point.json
esse/data/example/core/abstract/vector.json
esse/data/example/core/primitive/1d_data_series.json
esse/data/example/core/primitive/3d_lattice.json
esse/data/example/core/primitive/array_of_3_booleans.json
esse/data/example/core/primitive/array_of_3_numbers.json
esse/data/example/core/primitive/array_of_ids.json
esse/data/example/core/primitive/axis.json
esse/data/example/core/primitive/scalar.json
esse/data/example/core/primitive/string.json
esse/data/example/core/reference/experiment.json
esse/data/example/core/reference/literature.json
esse/data/example/core/reference/modeling.json
esse/data/example/core/reference/experiment/condition.json
esse/data/example/core/reference/experiment/location.json
esse/data/example/core/reference/literature/name.json
esse/data/example/core/reference/literature/pages.json
esse/data/example/core/reference/modeling/exabyte.json
esse/data/example/core/reusable/atomic_vectors.json
esse/data/example/core/reusable/band_gap.json
esse/data/example/core/reusable/energy.json
esse/data/example/core/reusable/file_metadata.json
esse/data/example/core/reusable/object_storage_container_data.json
esse/data/example/job/compute.json
esse/data/example/method/categorized_method.json
esse/data/example/method/method_parameters.json
esse/data/example/methods_directory/legacy/localorbital.json
esse-2023.12.25.post0.dist-info/LICENSE.md
esse-2023.12.25.post0.dist-info/METADATA
esse-2023.12.25.post0.dist-info/WHEEL
esse-2023.12.25.post0.dist-info/top_level.txt
esse-2023.12.25.post0.dist-info/RECORD
