Metadata-Version: 2.1
Name: esse
Version: 2023.12.25.post0
Summary: Exabyte Source of Schemas and Examples
Home-page: https://github.com/Exabyte-io/exabyte-esse
Author: Exabyte Inc.
Author-email: info@exabyte.io
Classifier: Programming Language :: Python
Classifier: Development Status :: 3 - Alpha
Classifier: Intended Audience :: Developers
Classifier: Topic :: Software Development
Classifier: License :: OSI Approved :: Apache Software License
Requires-Python: >=3.6
License-File: LICENSE.md
Requires-Dist: pyyaml <6,>=4.2b1
Requires-Dist: jsonschema ==2.6.0
Requires-Dist: python-slugify ==2.0.1
Requires-Dist: exabyte-json-include >=2020.10.19
Provides-Extra: test
Requires-Dist: coverage[toml] >=5.3 ; extra == 'test'
